deltacat/__init__.py
deltacat/constants.py
deltacat/exceptions.py
deltacat/logs.py
deltacat/aws/__init__.py
deltacat/aws/clients.py
deltacat/aws/constants.py
deltacat/aws/s3u.py
deltacat/aws/redshift/__init__.py
deltacat/aws/redshift/model/__init__.py
deltacat/aws/redshift/model/manifest.py
deltacat/catalog/__init__.py
deltacat/catalog/delegate.py
deltacat/catalog/interface.py
deltacat/catalog/model/__init__.py
deltacat/catalog/model/catalog.py
deltacat/catalog/model/table_definition.py
deltacat/compute/__init__.py
deltacat/compute/compactor/__init__.py
deltacat/compute/compactor/compaction_session.py
deltacat/compute/compactor/model/__init__.py
deltacat/compute/compactor/model/delta_annotated.py
deltacat/compute/compactor/model/delta_file_envelope.py
deltacat/compute/compactor/model/delta_file_locator.py
deltacat/compute/compactor/model/materialize_result.py
deltacat/compute/compactor/model/primary_key_index.py
deltacat/compute/compactor/model/pyarrow_write_result.py
deltacat/compute/compactor/model/round_completion_info.py
deltacat/compute/compactor/model/sort_key.py
deltacat/compute/compactor/steps/__init__.py
deltacat/compute/compactor/steps/dedupe.py
deltacat/compute/compactor/steps/hash_bucket.py
deltacat/compute/compactor/steps/materialize.py
deltacat/compute/compactor/steps/rehash/__init__.py
deltacat/compute/compactor/steps/rehash/rehash_bucket.py
deltacat/compute/compactor/steps/rehash/rewrite_index.py
deltacat/compute/compactor/utils/__init__.py
deltacat/compute/compactor/utils/io.py
deltacat/compute/compactor/utils/primary_key_index.py
deltacat/compute/compactor/utils/round_completion_file.py
deltacat/compute/compactor/utils/system_columns.py
deltacat/compute/metastats/__init__.py
deltacat/compute/metastats/meta_stats.py
deltacat/compute/metastats/stats.py
deltacat/compute/metastats/config/__init__.py
deltacat/compute/metastats/model/__init__.py
deltacat/compute/metastats/model/partition_stats_dict.py
deltacat_fork-0.1.14.dist-info/LICENSE
deltacat_fork-0.1.14.dist-info/METADATA
deltacat_fork-0.1.14.dist-info/WHEEL
deltacat_fork-0.1.14.dist-info/top_level.txt
deltacat_fork-0.1.14.dist-info/RECORD
