Metadata-Version: 2.1
Name: deltacat-fork
Version: 0.1.14
Summary: A scalable, fast, ACID-compliant Data Catalog powered by Ray.
Home-page: https://github.com/ray-project/deltacat
Author: Ray Team
License: UNKNOWN
Platform: UNKNOWN
Classifier: Development Status :: 4 - Beta
Classifier: Intended Audience :: Developers
Classifier: Programming Language :: Python :: 3 :: Only
Classifier: Programming Language :: Python :: 3.7
Classifier: Programming Language :: Python :: 3.8
Classifier: Programming Language :: Python :: 3.9
Classifier: Operating System :: OS Independent
Requires-Python: >=3.7
Requires-Dist: boto3 (==1.20.24)
Requires-Dist: numpy (==1.21.5)
Requires-Dist: pandas (==1.3.5)
Requires-Dist: pyarrow (==10.0.1)
Requires-Dist: pydantic (==1.10.4)
Requires-Dist: ray[default] (==2.0.0)
Requires-Dist: s3fs (==2022.2.0)
Requires-Dist: tenacity (==8.1.0)
Requires-Dist: typing-extensions (==4.4.0)
